inboxtracker/__init__.py
inboxtracker/base.py
inboxtracker/campaigns.py
inboxtracker/deliverability.py
inboxtracker/domains.py
inboxtracker/exceptions.py
inboxtracker/intelliseeds.py
inboxtracker/ping.py
inboxtracker/postmaster_tools.py
inboxtracker/regions.py
inboxtracker/seeds.py
inboxtracker/spam_trap.py
test/__init__.py
test/test_base.py
test/test_campaigns.py
test/test_deliverability.py
test/test_domains.py
test/test_intelliseeds.py
test/test_ping.py
test/test_postmaster_tools.py
test/test_regions.py
test/test_seeds.py
test/test_spam_trap.py
inboxtracker-1.2.1.dist-info/LICENSE
inboxtracker-1.2.1.dist-info/METADATA
inboxtracker-1.2.1.dist-info/WHEEL
inboxtracker-1.2.1.dist-info/top_level.txt
inboxtracker-1.2.1.dist-info/RECORD
